radio/__init__.py
radio_class-0.1.0.dist-info/DESCRIPTION.rst
radio_class-0.1.0.dist-info/METADATA
radio_class-0.1.0.dist-info/RECORD
radio_class-0.1.0.dist-info/WHEEL
radio_class-0.1.0.dist-info/metadata.json
radio_class-0.1.0.dist-info/top_level.txt
